./.gitignore
./Dockerfile
./PKG-INFO
./README.md
./README_EN.md
./pyproject.toml
./requirements.txt
./test_mcp.py
./uv.lock
./xiaohongshu_mcp.py
iflow_mcp_redbook_search_comment_mcp-2.0.1.dist-info/METADATA
iflow_mcp_redbook_search_comment_mcp-2.0.1.dist-info/WHEEL
iflow_mcp_redbook_search_comment_mcp-2.0.1.dist-info/entry_points.txt
iflow_mcp_redbook_search_comment_mcp-2.0.1.dist-info/RECORD
