Metadata-Version: 2.4
Name: iflow-mcp_redbook-search-comment-mcp
Version: 2.0.1
Summary: 小红书自动搜索评论工具（MCP Server 2.0）
Project-URL: Homepage, https://github.com/iflow-mcp/Redbook-Search-Comment-MCP2.0
Project-URL: Repository, https://github.com/iflow-mcp/Redbook-Search-Comment-MCP2.0
Author: chenningling
License: MIT
Requires-Python: >=3.10
Requires-Dist: asyncio==3.4.3
Requires-Dist: fastapi>=0.95.1
Requires-Dist: fastmcp
Requires-Dist: mcp[cli]
Requires-Dist: numpy>=1.26.4
Requires-Dist: pandas>=2.1.1
Requires-Dist: playwright>=1.40.0
Requires-Dist: pytest-playwright>=0.4.0
Requires-Dist: python-dotenv==1.0.0
Requires-Dist: requests==2.31.0
Requires-Dist: schedule==1.2.0
Requires-Dist: tqdm==4.66.1
Requires-Dist: uvicorn>=0.22.0
